wallthick/__init__.py
wallthick/api5l.py
wallthick/cli.py
wallthick/dnvf101.py
wallthick/pd8010.py
wallthick-0.0.8.dist-info/METADATA
wallthick-0.0.8.dist-info/RECORD
wallthick-0.0.8.dist-info/WHEEL
wallthick-0.0.8.dist-info/entry_points.txt
wallthick-0.0.8.dist-info/top_level.txt
