Metadata-Version: 2.1
Name: wallthick
Version: 0.0.8
Summary: PD8010 wall thickness calculations.
Home-page: https://github.com/benranderson/wallthick
Author: Ben Randerson
Author-email: ben.m.randerson@gmail.com
License: MIT License
Keywords: wall thickness engineering pipelines
Platform: UNKNOWN
Classifier: Topic :: Scientific/Engineering
Classifier: License :: OSI Approved :: MIT License
Classifier: Programming Language :: Python
Classifier: Programming Language :: Python :: 3
Classifier: Programming Language :: Python :: 3.6
Requires-Python: >=3.4.0
Requires-Dist: click
Requires-Dist: scipy
